{"LastInsertedClientId":4,"LastInsertedTherapistId":3,"LastInsertedExerciseId":0,"LastInsertedMedicineId":0,"LastInsertedTreatmentId":0,"LastInsertedPrescriptionId":4,"LastInsertedSessionId":16,"LastInsertedServiceId":14,"SessionDuration":1,"Clients":[{"ClientAppointments":[],"ClientPrescriptions":[],"Id":1,"FirstName":"weawe","LastName":"waeawe","Username":"aweawe","Password":"aweawe"},{"ClientAppointments":[1,2,3,4,10,11,12],"ClientPrescriptions":[],"Id":2,"FirstName":"rodrigo","LastName":"tester","Username":"igo","Password":"1234"},{"ClientAppointments":[15],"ClientPrescriptions":[],"Id":3,"FirstName":"jervasio","LastName":"josefine","Username":"unicornio","Password":"1234"},{"ClientAppointments":[],"ClientPrescriptions":[],"Id":4,"FirstName":"Joao","LastName":"Sin","Username":"jj","Password":"1234"}],"Exercises":[{"Intensity":5,"SuggestedSchedule":"Manha","Id":7,"Name":"teste"},{"Intensity":10,"SuggestedSchedule":"Manha","Id":8,"Name":"Lunge"},{"Intensity":8,"SuggestedSchedule":"Noite","Id":9,"Name":"Pistol Squats"},{"Intensity":7,"SuggestedSchedule":"11:00","Id":13,"Name":"Squats"}],"Medicines":[{"Dosage":"400mg","TimeOfDayToTakeMedicine":"Noite","Id":1,"Name":"Brufen"},{"Dosage":"400mg","TimeOfDayToTakeMedicine":"Noite","Id":2,"Name":"Brufen"},{"Dosage":"400mg","TimeOfDayToTakeMedicine":"Noite","Id":3,"Name":"Brufen"},{"Dosage":"400mg","TimeOfDayToTakeMedicine":"Noite","Id":4,"Name":"Brufen"},{"Dosage":"400mg","TimeOfDayToTakeMedicine":"Noite","Id":5,"Name":"Brufen"},{"Dosage":"400mg","TimeOfDayToTakeMedicine":"Noite","Id":6,"Name":"Brufen"},{"Dosage":"100mg","TimeOfDayToTakeMedicine":"noite","Id":11,"Name":"brufen"},{"Dosage":"1mg","TimeOfDayToTakeMedicine":"Tarde","Id":12,"Name":"Medicare"}],"Services":[],"Treatments":[{"Duration":"12 meses","Type":"Anti-cancro","Id":10,"Name":"Quimio-terapia"},{"Duration":"6 meses","Type":"Terapia anti cancro","Id":14,"Name":"Radio-terapia"}],"Therapists":[{"TherapistPrescriptions":[1,2,3],"TherapistSessions":[10,11,12],"Id":1,"FirstName":"tj","LastName":"why","Username":"tj","Password":"1234"},{"TherapistPrescriptions":[],"TherapistSessions":[],"Id":2,"FirstName":"testeAcesso","LastName":"Suceed","Username":"teste","Password":"1234"},{"TherapistPrescriptions":[4],"TherapistSessions":[15],"Id":3,"FirstName":"Maria","LastName":"Albertina","Username":"maria","Password":"1234"}],"Sessions":[{"Id":10,"AssignedTherapistId":1,"AssignedClientId":2,"SessionDate":"2021-09-17T13:00:00","TheraphistSessionNote":"","SessionPrescriptionId":-1},{"Id":11,"AssignedTherapistId":1,"AssignedClientId":2,"SessionDate":"2021-09-16T14:00:00","TheraphistSessionNote":"","SessionPrescriptionId":-1},{"Id":12,"AssignedTherapistId":1,"AssignedClientId":2,"SessionDate":"2021-09-21T11:00:00","TheraphistSessionNote":"","SessionPrescriptionId":3},{"Id":15,"AssignedTherapistId":3,"AssignedClientId":3,"SessionDate":"2021-09-14T15:00:00","TheraphistSessionNote":"","SessionPrescriptionId":4}],"Prescriptions":[{"Id":1,"TherapistsWithAcess":[],"PrescribedServices":[1],"ClientId":2,"PrescriptionAuthorId":1},{"Id":2,"TherapistsWithAcess":[2],"PrescribedServices":[1,8],"ClientId":2,"PrescriptionAuthorId":1},{"Id":3,"TherapistsWithAcess":[2],"PrescribedServices":[9],"ClientId":2,"PrescriptionAuthorId":1},{"Id":4,"TherapistsWithAcess":[2],"PrescribedServices":[2,8],"ClientId":3,"PrescriptionAuthorId":3}]}