{"LastInsertedClientId":1,"LastInsertedTherapistId":0,"LastInsertedExerciseId":0,"LastInsertedMedicineId":0,"LastInsertedTreatmentId":0,"LastInsertedServiceId":0,"LastInsertedUserId":0,"LastInsertedPrescriptionId":0,"LastInsertedSessionId":0,"Clients":[{"ClientAppointments":null,"ClientPrescriptions":null,"Id":1,"FirstName":"Rodrigo","LastName":"","Username":"igo","Password":"1234"},{"ClientAppointments":null,"ClientPrescriptions":null,"Id":1,"FirstName":"Joao","LastName":"","Username":"jo","Password":"1234"},{"ClientAppointments":[],"ClientPrescriptions":[],"Id":0,"FirstName":"TTT","LastName":"DDD","Username":"qwerty","Password":"1234"},{"ClientAppointments":[],"ClientPrescriptions":[],"Id":1,"FirstName":"Tester","LastName":"TesterLastName","Username":"TesterUser","Password":"TesterPassword"},{"ClientAppointments":[],"ClientPrescriptions":[],"Id":1,"FirstName":"dawdawdg","LastName":"aweg","Username":"gawgawgwae","Password":"gwagwaewq"},{"ClientAppointments":[],"ClientPrescriptions":[],"Id":1,"FirstName":"Rodrigoo","LastName":"TesterRodrigo","Username":"Username","Password":"1234"}],"Exercises":[],"Medicines":[],"Services":[],"Therapists":null,"Treatments":[],"Prescriptions":null,"Users":[],"Sessions":null}